sprw/__init__.py
sprw/io/__init__.py
sprw/io/assistant.py
sprw/io/aws.py
sprw/io/config.py
sprw/io/iot.py
sprw/io/print.py
sprw/io/exceptions/SPRWIoTExceptions.py
sprw/io/exceptions/__init__.py
sprw/io/speech_recognition/__init__.py
sprw/io/speech_recognition/__main__.py
sprw_iot-1.7.dist-info/METADATA
sprw_iot-1.7.dist-info/WHEEL
sprw_iot-1.7.dist-info/top_level.txt
sprw_iot-1.7.dist-info/RECORD
